{
  "timestamp": "2026-04-17T22:37:59.036307",
  "credit_stress_score": 13.3333,
  "credit_stress_label": "LOW",
  "n_danger": 0,
  "n_warning": 2,
  "n_ok": 4,
  "parallel_2008": false,
  "signals": {
    "hy_divergence": {
      "divergence_1m": 4.6,
      "divergence_3m": 0.78,
      "hyg_1m": 1.69,
      "hyg_3m": 0.61,
      "sp500_1m": 6.29,
      "rebounding": true,
      "diverging": false,
      "status": "OK"
    },
    "cds_proxy": {
      "spread_zscore": -1.28,
      "widening": false,
      "status": "OK"
    },
    "bank_loans": {
      "bkln_1m": 0.67,
      "bkln_3m": -0.78,
      "bkln_drawdown": -0.88,
      "status": "OK"
    },
    "oil_trigger": {
      "price": 94.7,
      "rise_from_low": 71.3,
      "above_100": false,
      "recession_threshold": false,
      "status": "WARNING"
    },
    "financials": {
      "kre_1m": 10.56,
      "kre_3m": 1.45,
      "xlf_1m": 6.79,
      "xlf_3m": -3.81,
      "insurance_1m": 5.2,
      "banks_weak": false,
      "status": "OK"
    },
    "tech_debt": {
      "software_1m": 0.02,
      "software_3m": -15.45,
      "cloud_1m": -5.09,
      "cloud_3m": -17.44,
      "status": "WARNING"
    }
  }
}