{
  "timestamp": "2026-04-09T22:39:51.653635",
  "composite_score": 0.1134,
  "risk_label": "LOW",
  "action": "WAIT / ACCUMULATE CASH",
  "buy_checklist": {
    "McClellan > -1 from below": false,
    "VIX > 35 (panic)": false,
    "Breadth < 12% above 200W": false,
    "30Y yield >= 5%": false,
    "S&P below 6475": false,
    "Oil > $120 (stress)": false
  },
  "active_buy_signals": 0,
  "metrics": {
    "sp500": 6782.8101,
    "sp500_drawdown": -2.8056,
    "vix": 21.04,
    "oil": 94.41,
    "gold": 4749.5,
    "bond_30y": 4.887,
    "yield_curve": 0.691,
    "pct_above_200": 62.7592,
    "pct_above_50": 63.6709,
    "mcclellan": 0.9573
  },
  "sector_performance": {
    "Energy": {
      "1M": 5.1,
      "3M": 29.5,
      "YTD": 28.0
    },
    "Financials": {
      "1M": 2.8,
      "3M": -7.5,
      "YTD": -6.3
    },
    "Technology": {
      "1M": 1.5,
      "3M": -3.2,
      "YTD": -1.7
    },
    "Healthcare": {
      "1M": -1.9,
      "3M": -5.9,
      "YTD": -3.4
    },
    "Industrials": {
      "1M": 0.5,
      "3M": 7.5,
      "YTD": 8.2
    },
    "Staples": {
      "1M": -2.9,
      "3M": 8.6,
      "YTD": 7.2
    },
    "Discretionary": {
      "1M": -3.0,
      "3M": -8.2,
      "YTD": -6.2
    },
    "Utilities": {
      "1M": 1.2,
      "3M": 12.5,
      "YTD": 9.1
    },
    "Real Estate": {
      "1M": -0.5,
      "3M": 6.4,
      "YTD": 5.8
    },
    "Materials": {
      "1M": 4.2,
      "3M": 11.4,
      "YTD": 12.7
    },
    "Comms": {
      "1M": -2.7,
      "3M": -2.5,
      "YTD": -2.3
    }
  }
}